napari_sam4is/__init__.py
napari_sam4is/_utils.py
napari_sam4is/_widget.py
napari_sam4is/napari.yaml
napari_sam4is/_tests/__init__.py
napari_sam4is/_tests/test_widget.py
napari_sam4is-0.1.1.dist-info/licenses/LICENSE
napari_sam4is-0.1.1.dist-info/METADATA
napari_sam4is-0.1.1.dist-info/WHEEL
napari_sam4is-0.1.1.dist-info/entry_points.txt
napari_sam4is-0.1.1.dist-info/top_level.txt
napari_sam4is-0.1.1.dist-info/RECORD
