Metadata-Version: 2.4
Name: napari-SAM4IS
Version: 0.1.1
Summary: Create annotations for instance segmentation using Segment Anything models
Author-email: Hiroki Kawai <h.kawai888@gmail.com>
License: Apache-2.0
Project-URL: Bug Tracker, https://github.com/hiroalchem/napari-SAM4IS/issues
Project-URL: Documentation, https://github.com/hiroalchem/napari-SAM4IS#README.md
Project-URL: Source Code, https://github.com/hiroalchem/napari-SAM4IS
Project-URL: User Support, https://github.com/hiroalchem/napari-SAM4IS/issues
Classifier: Development Status :: 2 - Pre-Alpha
Classifier: Framework :: napari
Classifier: Intended Audience :: Developers
Classifier: Operating System :: OS Independent
Classifier: Programming Language :: Python
Classifier: Programming Language :: Python :: 3
Classifier: Programming Language :: Python :: 3 :: Only
Classifier: Programming Language :: Python :: 3.8
Classifier: Programming Language :: Python :: 3.9
Classifier: Programming Language :: Python :: 3.10
Classifier: Programming Language :: Python :: 3.11
Classifier: Topic :: Scientific/Engineering :: Image Processing
Requires-Python: >=3.8
License-File: LICENSE
Requires-Dist: numpy>=1.20.0
Requires-Dist: magicgui>=0.7.0
Requires-Dist: qtpy>=2.0.0
Requires-Dist: torch>=1.12.0
Requires-Dist: torchvision>=0.13.0
Requires-Dist: scikit-image>=0.19.0
Requires-Dist: napari[all]>=0.4.17
Requires-Dist: requests>=2.25.0
Requires-Dist: urllib3>=1.26.0
Requires-Dist: Pillow>=8.0.0
Provides-Extra: testing
Requires-Dist: tox; extra == "testing"
Requires-Dist: pytest>=6.0; extra == "testing"
Requires-Dist: pytest-cov; extra == "testing"
Requires-Dist: pytest-qt; extra == "testing"
Requires-Dist: pyqt5; extra == "testing"
Provides-Extra: dev
Requires-Dist: black>=22.0; extra == "dev"
Requires-Dist: ruff>=0.1.0; extra == "dev"
Requires-Dist: pre-commit; extra == "dev"
Dynamic: license-file
